rebalancedcv/__init__.py
rebalancedcv/classification.py
rebalancedcv/regression.py
rebalancedcv-0.1.0.dist-info/licenses/LICENSE
rebalancedcv-0.1.0.dist-info/METADATA
rebalancedcv-0.1.0.dist-info/WHEEL
rebalancedcv-0.1.0.dist-info/top_level.txt
rebalancedcv-0.1.0.dist-info/RECORD
